{
  "$schema": "http://json-schema.org/draft-06/schema#",
  "id": "http://hl7.org/fhir/json-schema/ClinicalImpression",
  "description": "A record of a clinical assessment performed to determine what problem(s) may affect the patient and before planning the treatments or management strategies that are best to manage a patient's condition.",
  "type": "object",
  "required": ["resourceType", "subject"],
  "properties": {
    "resourceType": { "const": "ClinicalImpression" },
    "id": { "type": "string", "description": "Logical id of this artifact" },
    "_id": { "type": "string", "description": "MongoDB primary key" },
    "meta": { "type": "object", "properties": { "versionId": { "type": "string" }, "lastUpdated": { "type": "string" }, "source": { "type": "string" }, "profile": { "type": "array", "items": { "type": "string" } }, "security": { "type": "array", "items": { "type": "object", "properties": { "system": { "type": "string" }, "code": { "type": "string" }, "display": { "type": "string" } } } }, "tag": { "type": "array", "items": { "type": "object", "properties": { "system": { "type": "string" }, "code": { "type": "string" }, "display": { "type": "string" } } } } } },
    "implicitRules": { "type": "string" },
    "language": { "type": "string" },
    "text": { "type": "object", "properties": { "status": { "type": "string" }, "div": { "type": "string" } } },
    "contained": { "type": "array", "items": { "type": "object" } },
    "extension": { "type": "array", "items": { "type": "object" } },
    "modifierExtension": { "type": "array", "items": { "type": "object" } },
    "identifier": { "type": "array", "items": { "type": "object", "properties": { "use": { "type": "string" }, "system": { "type": "string" }, "value": { "type": "string" } } } },
    "status": { "type": "string", "enum": ["in-progress", "completed", "entered-in-error"] },
    "statusReason": { "type": "object", "properties": { "coding": { "type": "array", "items": { "type": "object", "properties": { "system": { "type": "string" }, "code": { "type": "string" }, "display": { "type": "string" } } } }, "text": { "type": "string" } } },
    "code": { "type": "object", "properties": { "coding": { "type": "array", "items": { "type": "object", "properties": { "system": { "type": "string" }, "code": { "type": "string" }, "display": { "type": "string" } } } }, "text": { "type": "string" } } },
    "description": { "type": "string" },
    "subject": { "type": "object", "properties": { "reference": { "type": "string" }, "display": { "type": "string" } } },
    "encounter": { "type": "object", "properties": { "reference": { "type": "string" }, "display": { "type": "string" } } },
    "effectiveDateTime": { "type": "string" },
    "effectivePeriod": { "type": "object", "properties": { "start": { "type": "string" }, "end": { "type": "string" } } },
    "date": { "type": "string" },
    "assessor": { "type": "object", "properties": { "reference": { "type": "string" }, "display": { "type": "string" } } },
    "previous": { "type": "object", "properties": { "reference": { "type": "string" }, "display": { "type": "string" } } },
    "problem": { "type": "array", "items": { "type": "object", "properties": { "reference": { "type": "string" }, "display": { "type": "string" } } } },
    "investigation": { "type": "array", "items": { "type": "object", "properties": { "code": { "type": "object", "properties": { "coding": { "type": "array", "items": { "type": "object", "properties": { "system": { "type": "string" }, "code": { "type": "string" }, "display": { "type": "string" } } } }, "text": { "type": "string" } } }, "item": { "type": "array", "items": { "type": "object", "properties": { "reference": { "type": "string" }, "display": { "type": "string" } } } } } } },
    "protocol": { "type": "array", "items": { "type": "string" } },
    "summary": { "type": "string" },
    "finding": { "type": "array", "items": { "type": "object", "properties": { "itemCodeableConcept": { "type": "object", "properties": { "coding": { "type": "array", "items": { "type": "object", "properties": { "system": { "type": "string" }, "code": { "type": "string" }, "display": { "type": "string" } } } }, "text": { "type": "string" } } }, "itemReference": { "type": "object", "properties": { "reference": { "type": "string" }, "display": { "type": "string" } } }, "basis": { "type": "string" } } } },
    "prognosisCodeableConcept": { "type": "array", "items": { "type": "object", "properties": { "coding": { "type": "array", "items": { "type": "object", "properties": { "system": { "type": "string" }, "code": { "type": "string" }, "display": { "type": "string" } } } }, "text": { "type": "string" } } } },
    "prognosisReference": { "type": "array", "items": { "type": "object", "properties": { "reference": { "type": "string" }, "display": { "type": "string" } } } },
    "supportingInfo": { "type": "array", "items": { "type": "object", "properties": { "reference": { "type": "string" }, "display": { "type": "string" } } } },
    "note": { "type": "array", "items": { "type": "object", "properties": { "text": { "type": "string" }, "time": { "type": "string" }, "authorReference": { "type": "object", "properties": { "reference": { "type": "string" }, "display": { "type": "string" } } }, "authorString": { "type": "string" } } } }
  }
}
